numpy_indexed/__init__.py
numpy_indexed/arraysetops.py
numpy_indexed/funcs.py
numpy_indexed/grouping.py
numpy_indexed/index.py
numpy_indexed/monkey_patch.py
numpy_indexed/semantics.py
numpy_indexed/utility.py
numpy_indexed_fedeful-0.0.0.dist-info/LICENSE
numpy_indexed_fedeful-0.0.0.dist-info/METADATA
numpy_indexed_fedeful-0.0.0.dist-info/WHEEL
numpy_indexed_fedeful-0.0.0.dist-info/top_level.txt
numpy_indexed_fedeful-0.0.0.dist-info/RECORD
