Metadata-Version: 2.1
Name: numpy-indexed-fedeful
Version: 0.0.0
Summary: This package contains functionality for indexed operations on numpy ndarrays, providing efficient vectorized functionality such as grouping and set operations.
Home-page: https://github.com/EelcoHoogendoorn/Numpy_arraysetops_EP
Author: Eelco Hoogendoorn
Author-email: hoogendoorn.eelco@gmail.com
License: Freely Distributable
Keywords: numpy group_by set-operations indexing
Platform: Any
Classifier: Development Status :: 4 - Beta
Classifier: Intended Audience :: Science/Research
Classifier: Intended Audience :: Developers
Classifier: Topic :: Utilities
Classifier: Topic :: Scientific/Engineering
Classifier: License :: Freely Distributable
Classifier: Operating System :: MacOS :: MacOS X
Classifier: Operating System :: Microsoft :: Windows
Classifier: Operating System :: POSIX
Classifier: Programming Language :: Python
Classifier: Programming Language :: Python :: 2.7
Classifier: Programming Language :: Python :: 3.5
License-File: LICENSE
Requires-Dist: numpy
Requires-Dist: future
